__main__.py
app.py
diff_processor.py
main.py
static/css/style.css
static/js/app.js
templates/index.html
contextforge-1.0.4.dist-info/METADATA
contextforge-1.0.4.dist-info/WHEEL
contextforge-1.0.4.dist-info/entry_points.txt
contextforge-1.0.4.dist-info/RECORD
