Metadata-Version: 2.4
Name: ContextForge
Version: 1.0.4
Summary: A web-based tool
Project-URL: Homepage, https://github.com/sethburkart123
Author: Seth Burkart
License: MIT
Keywords: code
Classifier: Development Status :: 4 - Beta
Classifier: Environment :: Web Environment
Classifier: Framework :: Flask
Classifier: Intended Audience :: Developers
Classifier: License :: OSI Approved :: MIT License
Classifier: Operating System :: OS Independent
Classifier: Programming Language :: Python :: 3
Classifier: Programming Language :: Python :: 3.8
Classifier: Programming Language :: Python :: 3.9
Classifier: Programming Language :: Python :: 3.10
Classifier: Programming Language :: Python :: 3.11
Classifier: Programming Language :: Python :: 3.12
Classifier: Topic :: Internet :: WWW/HTTP :: WSGI :: Application
Classifier: Topic :: Software Development
Requires-Python: >=3.8
Requires-Dist: flask>=2.3.0
Requires-Dist: pathlib2>=2.3.0
Requires-Dist: platformdirs>=4.3.6
Requires-Dist: tiktoken>=0.7.0
Requires-Dist: waitress>=2.1.0
Requires-Dist: watchdog>=4.0.2
